lensai_profiler_tf/__init__.py
lensai_profiler_tf/metrics.py
lensai_profiler_tf/sketches.py
tests/__init__.py
tests/test_metrics.py
lensai_profiler_tf-0.1.0.dist-info/LICENSE
lensai_profiler_tf-0.1.0.dist-info/METADATA
lensai_profiler_tf-0.1.0.dist-info/WHEEL
lensai_profiler_tf-0.1.0.dist-info/top_level.txt
lensai_profiler_tf-0.1.0.dist-info/RECORD
