Metadata-Version: 2.1
Name: lensai-profiler-tf
Version: 0.1.0
Summary: A library for computing image metrics and updating KLL sketches using Tensorflow while training.
Home-page: https://github.com/lens-ai/lensai_training_tensorflow
Author: Venkata Pydipalli
Author-email: vsnm.tej@gmail.com
Classifier: Programming Language :: Python :: 3
Classifier: License :: OSI Approved :: MIT License
Classifier: Operating System :: OS Independent
Requires-Python: >=3.6
License-File: LICENSE
Requires-Dist: tensorflow
Requires-Dist: numpy
Requires-Dist: datasketches
